starsearch/__init__.py
starsearch/core.py
starsearch/phase3Archive.py
starsearch/rawArchive.py
starsearch/utils.py
starsearch-0.4.1.dist-info/LICENSE
starsearch-0.4.1.dist-info/METADATA
starsearch-0.4.1.dist-info/WHEEL
starsearch-0.4.1.dist-info/top_level.txt
starsearch-0.4.1.dist-info/RECORD
